pytector/__init__.py
pytector/detector.py
pytector-0.2.0.dist-info/licenses/LICENSE
pytector-0.2.0.dist-info/METADATA
pytector-0.2.0.dist-info/WHEEL
pytector-0.2.0.dist-info/top_level.txt
pytector-0.2.0.dist-info/RECORD
