Metadata-Version: 2.4
Name: pytector
Version: 0.2.0
Summary: A package for detecting prompt injections in text using Open-Source LLMs.
Home-page: https://github.com/MaxMLang/pytector
Author: Max Melchior Lang
Author-email: langmaxmelchior@gmail.com
Classifier: Programming Language :: Python :: 3
Classifier: License :: OSI Approved :: MIT License
Classifier: Operating System :: OS Independent
Classifier: Development Status :: 3 - Alpha
Requires-Python: >=3.9
License-File: LICENSE
Requires-Dist: transformers>=4.0.0
Requires-Dist: validators
Requires-Dist: torch
Requires-Dist: groq
Provides-Extra: gguf
Requires-Dist: llama-cpp-python>=0.2.0; extra == "gguf"
Provides-Extra: test
Requires-Dist: pytest>=8.0; extra == "test"
Dynamic: author
Dynamic: author-email
Dynamic: classifier
Dynamic: description
Dynamic: description-content-type
Dynamic: home-page
Dynamic: license-file
Dynamic: provides-extra
Dynamic: requires-dist
Dynamic: requires-python
Dynamic: summary
